yyimg/000998.png.py
yyimg/__init__.py
yyimg/augments.py
yyimg/tools.py
yyimg/utils.py
yyimg/version.py
yyimg-1.0.2.dist-info/LICENSE
yyimg-1.0.2.dist-info/METADATA
yyimg-1.0.2.dist-info/WHEEL
yyimg-1.0.2.dist-info/top_level.txt
yyimg-1.0.2.dist-info/RECORD
