Metadata-Version: 2.1
Name: yyimg
Version: 1.0.2
Summary: image tools for deep learning
Home-page: https://github.com/YunYang1994/yyimg.git
Author: YunYang1994
Author-email: dreameryangyun@sjtu.edu.cn
License: UNKNOWN
Keywords: deep-learning,image
Platform: UNKNOWN
